{
  "indexes": [
    {
      "collectionGroup": "clients",
      "queryScope": "COLLECTION",
      "fields": [
        {
          "fieldPath": "executiveId",
          "order": "ASCENDING"
        },
        {
          "fieldPath": "createdAt",
          "order": "DESCENDING"
        }
      ]
    },
    {
      "collectionGroup": "ventas",
      "queryScope": "COLLECTION",
      "fields": [
        {
          "fieldPath": "segmento",
          "order": "ASCENDING"
        },
        {
          "fieldPath": "fechaVenta",
          "order": "ASCENDING"
        }
      ]
    }
  ],
  "fieldOverrides": []
}
